assets/pagating_block_diagram.png
assets/images/figures/all_units_gateflow.png
assets/images/figures/enhanced_transformer_results.png
assets/images/figures/paGELU_gateflow.png
assets/images/figures/paGELU_transformer_alpha0.50.png
assets/images/figures/paGLU_gateflow.png
assets/images/figures/paGLU_transformer_alpha0.50.png
assets/images/figures/paGTU_gateflow.png
assets/images/figures/paGTU_transformer_alpha0.50.png
assets/images/figures/paMishU_gateflow.png
assets/images/figures/paMishU_transformer_alpha0.50.png
assets/images/figures/paReGLU_gateflow.png
assets/images/figures/paReGLU_transformer_alpha0.50.png
assets/images/figures/paSiLU_gateflow.png
assets/images/figures/paSiLU_transformer_alpha0.50.png
assets/images/figures/paSwishU_gateflow.png
assets/images/figures/paSwishU_transformer_alpha0.50.png
assets/images/figures/transformer_comparison.png
assets/images/plots/all_units_gateflow.png
assets/images/plots/combined_transformer_results.png
assets/images/plots/enhanced_transformer_results.png
assets/images/plots/paGELU_gateflow.png
assets/images/plots/paGELU_transformer_alpha0.50.png
assets/images/plots/paGLU_gateflow.png
assets/images/plots/paGLU_transformer_alpha0.50.png
assets/images/plots/paGTU_gateflow.png
assets/images/plots/paGTU_transformer_alpha0.50.png
assets/images/plots/paMishU_alpha_comparison.png
assets/images/plots/paMishU_gateflow.png
assets/images/plots/paMishU_transformer_alpha0.50.png
assets/images/plots/paReGLU_gateflow.png
assets/images/plots/paReGLU_transformer_alpha0.50.png
assets/images/plots/paSiLU_gateflow.png
assets/images/plots/paSiLU_transformer_alpha0.50.png
assets/images/plots/paSwishU_gateflow.png
assets/images/plots/paSwishU_transformer_alpha0.50.png
assets/images/plots/unit_comparison.png
coreml_export/export_to_coreml.py
datamodules/cifar10_datamodule.py
examples/train_pagru_example.py
experiments/benchmark_gateflow.py
experiments/enhance_transformer_visualization.py
experiments/enhanced_visualize_transformer_results.py
pagating-0.1.0.dist-info/licenses/LICENSE
pagating-0.1.0.dist-info/METADATA
pagating-0.1.0.dist-info/WHEEL
pagating-0.1.0.dist-info/top_level.txt
pagating-0.1.0.dist-info/RECORD
