Metadata-Version: 2.4
Name: paGating
Version: 0.1.0
Summary: Parameterized Activation Gating Framework for Flexible and Efficient Neural Networks
Home-page: https://github.com/guglxni/paGating
Author: Aaryan Guglani
Author-email: Aaryan Guglani <aaryanguglani.cs21@rvce.edu.in>
Maintainer-email: Aaryan Guglani <aaryanguglani.cs21@rvce.edu.in>
License-Expression: Apache-2.0
Project-URL: Homepage, https://github.com/guglxni/paGating
Project-URL: Documentation, https://github.com/guglxni/paGating#readme
Project-URL: Repository, https://github.com/guglxni/paGating
Project-URL: Issues, https://github.com/guglxni/paGating/issues
Project-URL: Changelog, https://github.com/guglxni/paGating/blob/master/CHANGELOG.md
Keywords: deep-learning,neural-networks,activation-functions,pytorch,gating,transformer,machine-learning
Classifier: Development Status :: 4 - Beta
Classifier: Intended Audience :: Developers
Classifier: Intended Audience :: Science/Research
Classifier: Operating System :: OS Independent
Classifier: Programming Language :: Python :: 3
Classifier: Programming Language :: Python :: 3.8
Classifier: Programming Language :: Python :: 3.9
Classifier: Programming Language :: Python :: 3.10
Classifier: Programming Language :: Python :: 3.11
Classifier: Programming Language :: Python :: 3.12
Classifier: Topic :: Scientific/Engineering :: Artificial Intelligence
Classifier: Topic :: Software Development :: Libraries :: Python Modules
Requires-Python: >=3.8
License-File: LICENSE
Requires-Dist: torch>=1.9.0
Requires-Dist: numpy>=1.19.0
Provides-Extra: dev
Requires-Dist: pytest>=6.0.0; extra == "dev"
Requires-Dist: pytest-cov>=2.0.0; extra == "dev"
Requires-Dist: black>=21.0.0; extra == "dev"
Requires-Dist: flake8>=3.9.0; extra == "dev"
Requires-Dist: mypy>=0.900; extra == "dev"
Provides-Extra: export
Requires-Dist: onnx>=1.14.0; extra == "export"
Requires-Dist: onnxruntime>=1.15.0; extra == "export"
Requires-Dist: coremltools>=7.0; extra == "export"
Provides-Extra: benchmark
Requires-Dist: matplotlib>=3.4.0; extra == "benchmark"
Requires-Dist: pandas>=1.3.0; extra == "benchmark"
Requires-Dist: seaborn>=0.11.0; extra == "benchmark"
Requires-Dist: tqdm>=4.61.0; extra == "benchmark"
Requires-Dist: pillow>=8.2.0; extra == "benchmark"
Requires-Dist: pyyaml; extra == "benchmark"
Provides-Extra: ml
Requires-Dist: transformers>=4.30.0; extra == "ml"
Requires-Dist: datasets>=2.0.0; extra == "ml"
Requires-Dist: accelerate>=0.20.0; extra == "ml"
Requires-Dist: tf-keras>=2.13.1; extra == "ml"
Dynamic: author
Dynamic: home-page
Dynamic: license-file
Dynamic: requires-python
